{"children":[{"leaf":false,"expanded":"false","iconCls":"settingIcon","details":null,"id":"0","text":"CEO","description":"Setting Basics of Application","children":[{"leaf":true,"expanded":"FALSE","iconCls":"monitorIcon","details":null,"id":"2","text":"Department","description":"Create Department","children":null},{"leaf":true,"expanded":"FALSE","iconCls":"bookIcon","details":null,"id":"3","text":"Designation","description":"Create Designation","children":null},{"leaf":true,"expanded":"FALSE","iconCls":"userIcon","details":null,"id":"4","text":"Employee","description":"Create Employee","children":null},{"leaf":true,"expanded":"FALSE","iconCls":"userIcon","details":null,"id":"9","text":"Request List","description":"Request List","children":null},{"leaf":true,"expanded":"FALSE","iconCls":"timeInIcon","details":null,"id":"5","text":"Entry","description":"Entry Point","children":null},{"leaf":true,"expanded":"FALSE","iconCls":"userIcon","details":null,"id":"9","text":"Request List","description":"Request List","children":null},{"leaf":true,"expanded":"FALSE","iconCls":"userIcon","details":null,"id":"1","text":"Search Visitors","description":"Search Visitors","children":null}]}],"success":"success"}